pyhachi/__init__.py
pyhachi/model.py
pyhachi/plugin.py
pyhachi/utils.py
pyhachi-0.2.4.dist-info/DESCRIPTION.rst
pyhachi-0.2.4.dist-info/METADATA
pyhachi-0.2.4.dist-info/RECORD
pyhachi-0.2.4.dist-info/WHEEL
pyhachi-0.2.4.dist-info/entry_points.txt
pyhachi-0.2.4.dist-info/metadata.json
pyhachi-0.2.4.dist-info/top_level.txt
